odoo8_addon_connector_dns-8.0.1.0.0.99.dev5-py2.7-nspkg.pth
odoo8_addon_connector_dns-8.0.1.0.0.99.dev5.dist-info/METADATA
odoo8_addon_connector_dns-8.0.1.0.0.99.dev5.dist-info/RECORD
odoo8_addon_connector_dns-8.0.1.0.0.99.dev5.dist-info/WHEEL
odoo8_addon_connector_dns-8.0.1.0.0.99.dev5.dist-info/namespace_packages.txt
odoo8_addon_connector_dns-8.0.1.0.0.99.dev5.dist-info/top_level.txt
odoo_addons/connector_dns/README.rst
odoo_addons/connector_dns/__init__.py
odoo_addons/connector_dns/__openerp__.py
odoo_addons/connector_dns/backend.py
odoo_addons/connector_dns/connector.py
odoo_addons/connector_dns/consumer.py
odoo_addons/connector_dns/data/dns_record_type.xml
odoo_addons/connector_dns/i18n/connector_dns.pot
odoo_addons/connector_dns/models/__init__.py
odoo_addons/connector_dns/models/dns_backend.py
odoo_addons/connector_dns/models/dns_record.py
odoo_addons/connector_dns/models/dns_record_type.py
odoo_addons/connector_dns/models/dns_zone.py
odoo_addons/connector_dns/security/dns.xml
odoo_addons/connector_dns/security/ir.model.access.csv
odoo_addons/connector_dns/static/description/icon.png
odoo_addons/connector_dns/tests/__init__.py
odoo_addons/connector_dns/tests/common.py
odoo_addons/connector_dns/tests/test_backend_adapter.py
odoo_addons/connector_dns/tests/test_base_exporter.py
odoo_addons/connector_dns/tests/test_batch_importer.py
odoo_addons/connector_dns/tests/test_binder.py
odoo_addons/connector_dns/tests/test_connector.py
odoo_addons/connector_dns/tests/test_consumer.py
odoo_addons/connector_dns/tests/test_delayed_batch_importer.py
odoo_addons/connector_dns/tests/test_direct_batch_importer.py
odoo_addons/connector_dns/tests/test_dns_deleter.py
odoo_addons/connector_dns/tests/test_dns_exporter.py
odoo_addons/connector_dns/tests/test_dns_import_mapper.py
odoo_addons/connector_dns/tests/test_dns_importer.py
odoo_addons/connector_dns/tests/models/__init__.py
odoo_addons/connector_dns/tests/models/test_dns_backend.py
odoo_addons/connector_dns/tests/models/test_dns_record.py
odoo_addons/connector_dns/tests/models/test_dns_record_type.py
odoo_addons/connector_dns/unit/__init__.py
odoo_addons/connector_dns/unit/backend_adapter.py
odoo_addons/connector_dns/unit/binder.py
odoo_addons/connector_dns/unit/delete_synchronizer.py
